peedeeff/__init__.py
peedeeff-0.0.1.dist-info/METADATA
peedeeff-0.0.1.dist-info/WHEEL
peedeeff-0.0.1.dist-info/top_level.txt
peedeeff-0.0.1.dist-info/RECORD
