Metadata-Version: 2.1
Name: peedeeff
Version: 0.0.1
Summary: Python Client for Peedeeff
Home-page: https://github.com/Peedeeff/python-client
Author: Charanjit Singh
Author-email: charanjitdotsingh@gmail.com
License: UNKNOWN
Platform: UNKNOWN
Classifier: Programming Language :: Python :: 3
Classifier: Operating System :: OS Independent
Requires-Python: >=3.6
